[11:46:16] [main/DEBUG] [FML/]: Injecting tracing printstreams for STDOUT/STDERR.
[11:46:16] [main/INFO] [FML/]: Forge Mod Loader version 7.99.16.1448 for Minecraft 1.7.10 loading
[11:46:16] [main/INFO] [FML/]: Java is Java HotSpot(TM) Client VM, version 1.8.0_60, running on Windows 10:x86:10.0, installed at C:\Program Files (x86)\Java\jre1.8.0_60
[11:46:16] [main/DEBUG] [FML/]: Java classpath at launch is C:\Users\Connor\Desktop\Projects\mc mod 1\forge\bin;C:\Users\Connor\.gradle\caches\minecraft\net\minecraftforge\forge\1.7.10-10.13.4.1448-1.7.10\forgeSrc-1.7.10-10.13.4.1448-1.7.10.jar;C:\Users\Connor\.gradle\caches\modules-2\files-2.1\net.minecraft\launchwrapper\1.11\9c0592c6e1e9ea296a70948081bd4cc84dda1289\launchwrapper-1.11.jar;C:\Users\Connor\.gradle\caches\modules-2\files-2.1\com.google.code.findbugs\jsr305\1.3.9\40719ea6961c0cb6afaeb6a921eaa1f6afd4cfdf\jsr305-1.3.9.jar;C:\Users\Connor\.gradle\caches\modules-2\files-2.1\org.ow2.asm\asm-debug-all\5.0.3\f9e364ae2a66ce2a543012a4668856e84e5dab74\asm-debug-all-5.0.3.jar;C:\Users\Connor\.gradle\caches\modules-2\files-2.1\com.typesafe.akka\akka-actor_2.11\2.3.3\ed62e9fc709ca0f2ff1a3220daa8b70a2870078e\akka-actor_2.11-2.3.3.jar;C:\Users\Connor\.gradle\caches\modules-2\files-2.1\com.typesafe\config\1.2.1\f771f71fdae3df231bcd54d5ca2d57f0bf93f467\config-1.2.1.jar;C:\Users\Connor\.gradle\caches\modules-2\files-2.1\org.scala-lang\scala-actors-migration_2.11\1.1.0\dfa8bc42b181d5b9f1a5dd147f8ae308b893eb6f\scala-actors-migration_2.11-1.1.0.jar;C:\Users\Connor\.gradle\caches\modules-2\files-2.1\org.scala-lang\scala-compiler\2.11.1\56ea2e6c025e0821f28d73ca271218b8dd04926a\scala-compiler-2.11.1.jar;C:\Users\Connor\.gradle\caches\modules-2\files-2.1\org.scala-lang.plugins\scala-continuations-library_2.11\1.0.2\e517c53a7e9acd6b1668c5a35eccbaa3bab9aac\scala-continuations-library_2.11-1.0.2.jar;C:\Users\Connor\.gradle\caches\modules-2\files-2.1\org.scala-lang.plugins\scala-continuations-plugin_2.11.1\1.0.2\f361a3283452c57fa30c1ee69448995de23c60f7\scala-continuations-plugin_2.11.1-1.0.2.jar;C:\Users\Connor\.gradle\caches\modules-2\files-2.1\org.scala-lang\scala-library\2.11.1\e11da23da3eabab9f4777b9220e60d44c1aab6a\scala-library-2.11.1.jar;C:\Users\Connor\.gradle\caches\modules-2\files-2.1\org.scala-lang\scala-parser-combinators_2.11\1.0.1\f05d7345bf5a58924f2837c6c1f4d73a938e1ff0\scala-parser-combinators_2.11-1.0.1.jar;C:\Users\Connor\.gradle\caches\modules-2\files-2.1\org.scala-lang\scala-reflect\2.11.1\6580347e61cc7f8e802941e7fde40fa83b8badeb\scala-reflect-2.11.1.jar;C:\Users\Connor\.gradle\caches\modules-2\files-2.1\org.scala-lang\scala-swing_2.11\1.0.1\b1cdd92bd47b1e1837139c1c53020e86bb9112ae\scala-swing_2.11-1.0.1.jar;C:\Users\Connor\.gradle\caches\modules-2\files-2.1\org.scala-lang\scala-xml_2.11\1.0.2\7a80ec00aec122fba7cd4e0d4cdd87ff7e4cb6d0\scala-xml_2.11-1.0.2.jar;C:\Users\Connor\.gradle\caches\modules-2\files-2.1\net.sf.jopt-simple\jopt-simple\4.5\6065cc95c661255349c1d0756657be17c29a4fd3\jopt-simple-4.5.jar;C:\Users\Connor\.gradle\caches\modules-2\files-2.1\lzma\lzma\0.0.1\521616dc7487b42bef0e803bd2fa3faf668101d7\lzma-0.0.1.jar;C:\Users\Connor\.gradle\caches\modules-2\files-2.1\com.mojang\realms\1.3.5\807ae355ee63583becd7ea60e76aab1532bb42e\realms-1.3.5.jar;C:\Users\Connor\.gradle\caches\modules-2\files-2.1\org.apache.commons\commons-compress\1.8.1\a698750c16740fd5b3871425f4cb3bbaa87f529d\commons-compress-1.8.1.jar;C:\Users\Connor\.gradle\caches\modules-2\files-2.1\org.apache.httpcomponents\httpclient\4.3.3\18f4247ff4572a074444572cee34647c43e7c9c7\httpclient-4.3.3.jar;C:\Users\Connor\.gradle\caches\modules-2\files-2.1\commons-logging\commons-logging\1.1.3\f6f66e966c70a83ffbdb6f17a0919eaf7c8aca7f\commons-logging-1.1.3.jar;C:\Users\Connor\.gradle\caches\modules-2\files-2.1\org.apache.httpcomponents\httpcore\4.3.2\31fbbff1ddbf98f3aa7377c94d33b0447c646b6e\httpcore-4.3.2.jar;C:\Users\Connor\.gradle\caches\modules-2\files-2.1\java3d\vecmath\1.3.1\a0ae4f51da409fa0c20fa0ca59e6bbc9413ae71d\vecmath-1.3.1.jar;C:\Users\Connor\.gradle\caches\modules-2\files-2.1\net.sf.trove4j\trove4j\3.0.3\42ccaf4761f0dfdfa805c9e340d99a755907e2dd\trove4j-3.0.3.jar;C:\Users\Connor\.gradle\caches\modules-2\files-2.1\com.ibm.icu\icu4j-core-mojang\51.2\63d216a9311cca6be337c1e458e587f99d382b84\icu4j-core-mojang-51.2.jar;C:\Users\Connor\.gradle\caches\modules-2\files-2.1\com.paulscode\codecjorbis\20101023\c73b5636faf089d9f00e8732a829577de25237ee\codecjorbis-20101023.jar;C:\Users\Connor\.gradle\caches\modules-2\files-2.1\com.paulscode\codecwav\20101023\12f031cfe88fef5c1dd36c563c0a3a69bd7261da\codecwav-20101023.jar;C:\Users\Connor\.gradle\caches\modules-2\files-2.1\com.paulscode\libraryjavasound\20101123\5c5e304366f75f9eaa2e8cca546a1fb6109348b3\libraryjavasound-20101123.jar;C:\Users\Connor\.gradle\caches\modules-2\files-2.1\com.paulscode\librarylwjglopenal\20100824\73e80d0794c39665aec3f62eee88ca91676674ef\librarylwjglopenal-20100824.jar;C:\Users\Connor\.gradle\caches\modules-2\files-2.1\com.paulscode\soundsystem\20120107\419c05fe9be71f792b2d76cfc9b67f1ed0fec7f6\soundsystem-20120107.jar;C:\Users\Connor\.gradle\caches\modules-2\files-2.1\io.netty\netty-all\4.0.10.Final\9e50bd52ffe257a0e2cd8d971688d6ce7d174325\netty-all-4.0.10.Final.jar;C:\Users\Connor\.gradle\caches\modules-2\files-2.1\com.google.guava\guava\17.0\9c6ef172e8de35fd8d4d8783e4821e57cdef7445\guava-17.0.jar;C:\Users\Connor\.gradle\caches\modules-2\files-2.1\org.apache.commons\commons-lang3\3.3.2\90a3822c38ec8c996e84c16a3477ef632cbc87a3\commons-lang3-3.3.2.jar;C:\Users\Connor\.gradle\caches\modules-2\files-2.1\commons-io\commons-io\2.4\b1b6ea3b7e4aa4f492509a4952029cd8e48019ad\commons-io-2.4.jar;C:\Users\Connor\.gradle\caches\modules-2\files-2.1\commons-codec\commons-codec\1.9\9ce04e34240f674bc72680f8b843b1457383161a\commons-codec-1.9.jar;C:\Users\Connor\.gradle\caches\modules-2\files-2.1\net.java.jinput\jinput\2.0.5\39c7796b469a600f72380316f6b1f11db6c2c7c4\jinput-2.0.5.jar;C:\Users\Connor\.gradle\caches\modules-2\files-2.1\net.java.jutils\jutils\1.0.0\e12fe1fda814bd348c1579329c86943d2cd3c6a6\jutils-1.0.0.jar;C:\Users\Connor\.gradle\caches\modules-2\files-2.1\com.google.code.gson\gson\2.2.4\a60a5e993c98c864010053cb901b7eab25306568\gson-2.2.4.jar;C:\Users\Connor\.gradle\caches\modules-2\files-2.1\com.mojang\authlib\1.5.16\ef1582b11fd0943d069cdcb72e99008ac209a283\authlib-1.5.16.jar;C:\Users\Connor\.gradle\caches\modules-2\files-2.1\org.apache.logging.log4j\log4j-api\2.0-beta9\1dd66e68cccd907880229f9e2de1314bd13ff785\log4j-api-2.0-beta9.jar;C:\Users\Connor\.gradle\caches\modules-2\files-2.1\org.apache.logging.log4j\log4j-core\2.0-beta9\678861ba1b2e1fccb594bb0ca03114bb05da9695\log4j-core-2.0-beta9.jar;C:\Users\Connor\.gradle\caches\modules-2\files-2.1\org.lwjgl.lwjgl\lwjgl\2.9.1\f58c5aabcef0e41718a564be9f8e412fff8db847\lwjgl-2.9.1.jar;C:\Users\Connor\.gradle\caches\modules-2\files-2.1\org.lwjgl.lwjgl\lwjgl_util\2.9.1\290d7ba8a1bd9566f5ddf16ad06f09af5ec9b20e\lwjgl_util-2.9.1.jar;C:\Users\Connor\.gradle\caches\modules-2\files-2.1\tv.twitch\twitch\5.16\1f55f009c61637c10c0acfb8b5ffc600f30044b4\twitch-5.16.jar;C:\Users\Connor\.gradle\caches\modules-2\files-2.1\org.scala-lang\scala-actors\2.11.0\8ccfb6541de179bb1c4d45cf414acee069b7f78b\scala-actors-2.11.0.jar;C:\Users\Connor\.gradle\caches\modules-2\files-2.1\org.scala-lang.modules\scala-xml_2.11\1.0.2\820fbca7e524b530fdadc594c39d49a21ea0337e\scala-xml_2.11-1.0.2.jar;C:\Users\Connor\.gradle\caches\modules-2\files-2.1\org.scala-lang.modules\scala-parser-combinators_2.11\1.0.1\f05d7345bf5a58924f2837c6c1f4d73a938e1ff0\scala-parser-combinators_2.11-1.0.1.jar;C:\Users\Connor\.gradle\caches\modules-2\files-2.1\net.java.jinput\jinput-platform\2.0.5\7ff832a6eb9ab6a767f1ade2b548092d0fa64795\jinput-platform-2.0.5-natives-linux.jar;C:\Users\Connor\.gradle\caches\modules-2\files-2.1\net.java.jinput\jinput-platform\2.0.5\385ee093e01f587f30ee1c8a2ee7d408fd732e16\jinput-platform-2.0.5-natives-windows.jar;C:\Users\Connor\.gradle\caches\modules-2\files-2.1\net.java.jinput\jinput-platform\2.0.5\53f9c919f34d2ca9de8c51fc4e1e8282029a9232\jinput-platform-2.0.5-natives-osx.jar;C:\Users\Connor\.gradle\caches\modules-2\files-2.1\tv.twitch\twitch-platform\5.16\7c6affe439099806a4f552da14c42f9d643d8b23\twitch-platform-5.16-natives-windows-32.jar;C:\Users\Connor\.gradle\caches\modules-2\files-2.1\tv.twitch\twitch-platform\5.16\39d0c3d363735b4785598e0e7fbf8297c706a9f9\twitch-platform-5.16-natives-windows-64.jar;C:\Users\Connor\.gradle\caches\modules-2\files-2.1\tv.twitch\twitch-platform\5.16\62503ee712766cf77f97252e5902786fd834b8c5\twitch-platform-5.16-natives-osx.jar;C:\Users\Connor\.gradle\caches\modules-2\files-2.1\tv.twitch\twitch-external-platform\4.5\18215140f010c05b9f86ef6f0f8871954d2ccebf\twitch-external-platform-4.5-natives-windows-32.jar;C:\Users\Connor\.gradle\caches\modules-2\files-2.1\tv.twitch\twitch-external-platform\4.5\c3cde57891b935d41b6680a9c5e1502eeab76d86\twitch-external-platform-4.5-natives-windows-64.jar;C:\Users\Connor\.gradle\caches\modules-2\files-2.1\org.lwjgl.lwjgl\lwjgl-platform\2.9.1\4c517eca808522457dd95ee8fc1fbcdbb602efbe\lwjgl-platform-2.9.1-natives-windows.jar;C:\Users\Connor\.gradle\caches\modules-2\files-2.1\org.lwjgl.lwjgl\lwjgl-platform\2.9.1\aa9aae879af8eb378e22cfc64db56ec2ca9a44d1\lwjgl-platform-2.9.1-natives-linux.jar;C:\Users\Connor\.gradle\caches\modules-2\files-2.1\org.lwjgl.lwjgl\lwjgl-platform\2.9.1\2d12c83fdfbc04ecabf02c7bc8cc54d034f0daac\lwjgl-platform-2.9.1-natives-osx.jar;C:\Users\Connor\.gradle\caches\minecraft\net\minecraftforge\forge\1.7.10-10.13.4.1448-1.7.10\start;C:\Users\Connor\Desktop\Projects\mc mod 1\workspace\mod1\bin;C:\Program Files (x86)\Java\jre1.8.0_60\lib\resources.jar;C:\Program Files (x86)\Java\jre1.8.0_60\lib\rt.jar;C:\Program Files (x86)\Java\jre1.8.0_60\lib\jsse.jar;C:\Program Files (x86)\Java\jre1.8.0_60\lib\jce.jar;C:\Program Files (x86)\Java\jre1.8.0_60\lib\charsets.jar;C:\Program Files (x86)\Java\jre1.8.0_60\lib\jfr.jar;C:\Program Files (x86)\Java\jre1.8.0_60\lib\ext\access-bridge-32.jar;C:\Program Files (x86)\Java\jre1.8.0_60\lib\ext\cldrdata.jar;C:\Program Files (x86)\Java\jre1.8.0_60\lib\ext\dnsns.jar;C:\Program Files (x86)\Java\jre1.8.0_60\lib\ext\jaccess.jar;C:\Program Files (x86)\Java\jre1.8.0_60\lib\ext\jfxrt.jar;C:\Program Files (x86)\Java\jre1.8.0_60\lib\ext\localedata.jar;C:\Program Files (x86)\Java\jre1.8.0_60\lib\ext\nashorn.jar;C:\Program Files (x86)\Java\jre1.8.0_60\lib\ext\sunec.jar;C:\Program Files (x86)\Java\jre1.8.0_60\lib\ext\sunjce_provider.jar;C:\Program Files (x86)\Java\jre1.8.0_60\lib\ext\sunmscapi.jar;C:\Program Files (x86)\Java\jre1.8.0_60\lib\ext\sunpkcs11.jar;C:\Program Files (x86)\Java\jre1.8.0_60\lib\ext\zipfs.jar;C:\Users\Connor\Desktop\Projects\mc mod 1\TinkersConstruct-master\TinkersConstruct-master\bin;C:\Users\Connor\.gradle\caches\modules-2\files-2.1\mantle\Mantle\1.7.10-0.3.2.jenkins187\3854db5e79ce0075b4226ede42d38d349364380e\Mantle-1.7.10-0.3.2.jenkins187-deobf.jar;C:\Users\Connor\.gradle\caches\modules-2\files-2.1\codechicken\CodeChickenLib\1.7.10-1.1.3.136\11a25c0b3c516f69997addf1cf1b7a38f7b8ee8b\CodeChickenLib-1.7.10-1.1.3.136-dev.jar;C:\Users\Connor\.gradle\caches\modules-2\files-2.1\codechicken\CodeChickenCore\1.7.10-1.0.6.43\7373bdc9ff72ff34dc85c42c0cf077ed7834065c\CodeChickenCore-1.7.10-1.0.6.43-dev.jar;C:\Users\Connor\.gradle\caches\modules-2\files-2.1\codechicken\NotEnoughItems\1.7.10-1.0.4.106\2f540c1402d458270f055d59244906fe199e046\NotEnoughItems-1.7.10-1.0.4.106-dev.jar;C:\Users\Connor\.gradle\caches\modules-2\files-2.1\codechicken\ForgeMultipart\1.7.10-1.1.2.334\62ec9d63f2bb752eb80abdfd2c9df493f9823d36\ForgeMultipart-1.7.10-1.1.2.334-dev.jar;C:\Users\Connor\Desktop\Projects\mc mod 1\TinkersConstruct-master\TinkersConstruct-master\build\dirtyArtifacts\forgeBin-1.7.10-10.13.3.1399-1.7.10.jar;C:\Users\Connor\.gradle\caches\minecraft\net\minecraftforge\forge\1.7.10-10.13.3.1399-1.7.10\start
[11:46:16] [main/DEBUG] [FML/]: Java library path at launch is C:\Program Files (x86)\Java\jre1.8.0_60\bin;C:\WINDOWS\Sun\Java\bin;C:\WINDOWS\system32;C:\WINDOWS;C:/Program Files (x86)/Java/jre1.8.0_60/bin/client;C:/Program Files (x86)/Java/jre1.8.0_60/bin;C:/Program Files (x86)/Java/jre1.8.0_60/lib/i386;C:\ProgramData\Oracle\Java\javapath;C:\Python33\;C:\Program Files (x86)\NVIDIA Corporation\PhysX\Common;C:\Program Files (x86)\Intel\iCLS Client\;C:\Program Files\Intel\iCLS Client\;C:\WINDOWS\system32;C:\WINDOWS;C:\WINDOWS\System32\Wbem;C:\WINDOWS\System32\WindowsPowerShell\v1.0\;C:\Program Files\Hewlett-Packard\SimplePass\;C:\Program Files\Intel\Intel(R) Management Engine Components\DAL;C:\Program Files\Intel\Intel(R) Management Engine Components\IPT;C:\Program Files (x86)\Intel\Intel(R) Management Engine Components\DAL;C:\Program Files (x86)\Intel\Intel(R) Management Engine Components\IPT;c:\Program Files (x86)\Microsoft SQL Server\110\Tools\Binn\;c:\Program Files\Microsoft SQL Server\110\Tools\Binn\;c:\Program Files\Microsoft SQL Server\110\DTS\Binn\;C:\Program Files (x86)\OpenVPN\bin;C:\Program Files\Git\cmd;C:\Users\Connor\Desktop\Projects\mc mod 1\eclipse-jee-mars-R-win32\eclipse;;.;C:/Users/Connor/.gradle/caches/minecraft/net/minecraft/minecraft_natives/1.7.10
[11:46:16] [main/INFO] [FML/]: Managed to load a deobfuscated Minecraft name- we are in a deobfuscated environment. Skipping runtime deobfuscation
[11:46:16] [main/DEBUG] [FML/]: Instantiating coremod class FMLCorePlugin
[11:46:16] [main/DEBUG] [FML/]: Added access transformer class cpw.mods.fml.common.asm.transformers.AccessTransformer to enqueued access transformers
[11:46:16] [main/DEBUG] [FML/]: Enqueued coremod FMLCorePlugin
[11:46:16] [main/DEBUG] [FML/]: Instantiating coremod class FMLForgePlugin
[11:46:16] [main/DEBUG] [FML/]: Added access transformer class net.minecraftforge.transformers.ForgeAccessTransformer to enqueued access transformers
[11:46:16] [main/DEBUG] [FML/]: Enqueued coremod FMLForgePlugin
[11:46:16] [main/DEBUG] [FML/]: All fundamental core mods are successfully located
[11:46:16] [main/INFO] [FML/]: Found a command line coremod : codechicken.nei.asm.NEICorePlugin
[11:46:16] [main/DEBUG] [FML/]: Instantiating coremod class NEICorePlugin
[11:46:16] [main/WARN] [FML/]: The coremod codechicken.nei.asm.NEICorePlugin does not have a MCVersion annotation, it may cause issues with this version of Minecraft
[11:46:16] [main/DEBUG] [FML/]: Enqueued coremod NEICorePlugin
[11:46:16] [main/INFO] [FML/]: Found a command line coremod : codechicken.core.launch.CodeChickenCorePlugin
[11:46:16] [main/DEBUG] [FML/]: Instantiating coremod class CodeChickenCorePlugin
[11:46:16] [main/WARN] [FML/]: The coremod codechicken.core.launch.CodeChickenCorePlugin does not have a MCVersion annotation, it may cause issues with this version of Minecraft
[11:46:17] [main/DEBUG] [FML/]: Added access transformer class codechicken.core.asm.CodeChickenAccessTransformer to enqueued access transformers
[11:46:17] [main/DEBUG] [FML/]: Enqueued coremod CodeChickenCorePlugin
[11:46:17] [main/INFO] [FML/]: Found a command line coremod : codechicken.core.launch.DepLoader
[11:46:17] [main/DEBUG] [FML/]: Instantiating coremod class DepLoader
[11:46:17] [main/WARN] [FML/]: The coremod codechicken.core.launch.DepLoader does not have a MCVersion annotation, it may cause issues with this version of Minecraft
[11:46:17] [main/DEBUG] [FML/]: Enqueued coremod DepLoader
[11:46:17] [main/DEBUG] [FML/]: Attempting to load commandline specified mods, relative to C:\Users\Connor\Desktop\Projects\mc mod 1\forge\.
[11:46:17] [main/DEBUG] [FML/]: Discovering coremods
[11:46:17] [main/DEBUG] [FML/]: Examining for coremod candidacy CodeChickenCore-1.7.10-1.0.4.29-dev.jar
[11:46:17] [main/TRACE] [FML/]: Adding CodeChickenCore-1.7.10-1.0.4.29-dev.jar to the list of known coremods, it will not be examined again
[11:46:17] [main/DEBUG] [FML/]: Instantiating coremod class CodeChickenCorePlugin
[11:46:17] [main/WARN] [FML/]: The coremod codechicken.core.launch.CodeChickenCorePlugin does not have a MCVersion annotation, it may cause issues with this version of Minecraft
[11:46:17] [main/DEBUG] [FML/]: Added access transformer class codechicken.core.asm.CodeChickenAccessTransformer to enqueued access transformers
[11:46:17] [main/DEBUG] [FML/]: Enqueued coremod CodeChickenCorePlugin
[11:46:17] [main/DEBUG] [FML/]: Examining for coremod candidacy CodeChickenLib-1.7.10-1.1.3.127-dev.jar
[11:46:17] [main/DEBUG] [FML/]: Not found coremod data in CodeChickenLib-1.7.10-1.1.3.127-dev.jar
[11:46:17] [main/DEBUG] [FML/]: Examining for coremod candidacy ForgeMultipart-1.7.10-1.2.0.345-dev.jar
[11:46:17] [main/TRACE] [FML/]: Found FMLCorePluginContainsFMLMod marker in ForgeMultipart-1.7.10-1.2.0.345-dev.jar, it will be examined later for regular @Mod instances
[11:46:17] [main/DEBUG] [FML/]: Instantiating coremod class DepLoader
[11:46:17] [main/WARN] [FML/]: The coremod codechicken.core.launch.DepLoader does not have a MCVersion annotation, it may cause issues with this version of Minecraft
[11:46:17] [main/DEBUG] [FML/]: Enqueued coremod DepLoader
[11:46:17] [main/DEBUG] [FML/]: Examining for coremod candidacy NotEnoughItems-1.7.10-1.0.3.74-dev.jar
[11:46:17] [main/TRACE] [FML/]: Adding NotEnoughItems-1.7.10-1.0.3.74-dev.jar to the list of known coremods, it will not be examined again
[11:46:17] [main/DEBUG] [FML/]: Instantiating coremod class NEICorePlugin
[11:46:17] [main/WARN] [FML/]: The coremod codechicken.nei.asm.NEICorePlugin does not have a MCVersion annotation, it may cause issues with this version of Minecraft
[11:46:17] [main/DEBUG] [FML/]: Enqueued coremod NEICorePlugin
[11:46:17] [main/INFO] [LaunchWrapper/]: Calling tweak class net.minecraftforge.gradle.tweakers.CoremodTweaker
[11:46:17] [main/INFO] [GradleStart/]: Injecting location in coremod cpw.mods.fml.relauncher.FMLCorePlugin
[11:46:17] [main/INFO] [GradleStart/]: Injecting location in coremod net.minecraftforge.classloading.FMLForgePlugin
[11:46:17] [main/INFO] [GradleStart/]: Injecting location in coremod codechicken.core.asm.MCPDeobfuscationTransformer.LoadPlugin
[11:46:17] [main/INFO] [GradleStart/]: Injecting location in coremod codechicken.nei.asm.NEICorePlugin
[11:46:17] [main/INFO] [GradleStart/]: Injecting location in coremod codechicken.core.launch.CodeChickenCorePlugin
[11:46:17] [main/INFO] [GradleStart/]: Injecting location in coremod codechicken.core.launch.DepLoader
[11:46:17] [main/INFO] [GradleStart/]: Injecting location in coremod codechicken.core.launch.CodeChickenCorePlugin
[11:46:17] [main/INFO] [GradleStart/]: Injecting location in coremod codechicken.core.launch.DepLoader
[11:46:17] [main/INFO] [GradleStart/]: Injecting location in coremod codechicken.nei.asm.NEICorePlugin
[11:46:17] [main/INFO] [LaunchWrapper/]: Loading tweak class name cpw.mods.fml.common.launcher.FMLInjectionAndSortingTweaker
[11:46:17] [main/INFO] [LaunchWrapper/]: Loading tweak class name cpw.mods.fml.common.launcher.FMLDeobfTweaker
[11:46:17] [main/INFO] [LaunchWrapper/]: Loading tweak class name net.minecraftforge.gradle.tweakers.AccessTransformerTweaker
[11:46:17] [main/INFO] [LaunchWrapper/]: Calling tweak class cpw.mods.fml.common.launcher.FMLInjectionAndSortingTweaker
[11:46:17] [main/INFO] [LaunchWrapper/]: Calling tweak class cpw.mods.fml.common.launcher.FMLInjectionAndSortingTweaker
[11:46:17] [main/INFO] [LaunchWrapper/]: Calling tweak class cpw.mods.fml.relauncher.CoreModManager$FMLPluginWrapper
[11:46:17] [main/DEBUG] [FML/]: Injecting coremod FMLCorePlugin {cpw.mods.fml.relauncher.FMLCorePlugin} class transformers
[11:46:17] [main/TRACE] [FML/]: Registering transformer cpw.mods.fml.common.asm.transformers.MarkerTransformer
[11:46:17] [main/TRACE] [FML/]: Registering transformer cpw.mods.fml.common.asm.transformers.SideTransformer
[11:46:17] [main/TRACE] [FML/]: Registering transformer cpw.mods.fml.common.asm.transformers.EventSubscriptionTransformer
[11:46:17] [main/DEBUG] [FML/]: Injection complete
[11:46:17] [main/DEBUG] [FML/]: Running coremod plugin for FMLCorePlugin {cpw.mods.fml.relauncher.FMLCorePlugin}
[11:46:17] [main/DEBUG] [FML/]: Running coremod plugin FMLCorePlugin
[11:46:17] [main/ERROR] [FML/]: The binary patch set is missing. Either you are in a development environment, or things are not going to work!
[11:46:19] [main/ERROR] [FML/]: FML appears to be missing any signature data. This is not a good thing
[11:46:19] [main/DEBUG] [FML/]: Coremod plugin class FMLCorePlugin run successfully
[11:46:19] [main/INFO] [LaunchWrapper/]: Calling tweak class cpw.mods.fml.relauncher.CoreModManager$FMLPluginWrapper
[11:46:19] [main/DEBUG] [FML/]: Injecting coremod FMLForgePlugin {net.minecraftforge.classloading.FMLForgePlugin} class transformers
[11:46:19] [main/TRACE] [FML/]: Registering transformer net.minecraftforge.classloading.FluidIdTransformer
[11:46:19] [main/DEBUG] [FML/]: Injection complete
[11:46:19] [main/DEBUG] [FML/]: Running coremod plugin for FMLForgePlugin {net.minecraftforge.classloading.FMLForgePlugin}
[11:46:19] [main/DEBUG] [FML/]: Running coremod plugin FMLForgePlugin
[11:46:19] [main/DEBUG] [FML/]: Coremod plugin class FMLForgePlugin run successfully
[11:46:19] [main/INFO] [LaunchWrapper/]: Calling tweak class cpw.mods.fml.relauncher.CoreModManager$FMLPluginWrapper
[11:46:19] [main/DEBUG] [FML/]: Injecting coremod CCCDeobfPlugin {codechicken.core.asm.MCPDeobfuscationTransformer$LoadPlugin} class transformers
[11:46:19] [main/DEBUG] [FML/]: Injection complete
[11:46:19] [main/DEBUG] [FML/]: Running coremod plugin for CCCDeobfPlugin {codechicken.core.asm.MCPDeobfuscationTransformer$LoadPlugin}
[11:46:19] [main/DEBUG] [FML/]: Running coremod plugin CCCDeobfPlugin
[11:47:05] [main/DEBUG] [FML/]: Coremod plugin class LoadPlugin run successfully
[11:47:05] [main/INFO] [LaunchWrapper/]: Calling tweak class cpw.mods.fml.relauncher.CoreModManager$FMLPluginWrapper
[11:47:05] [main/DEBUG] [FML/]: Injecting coremod NEICorePlugin {codechicken.nei.asm.NEICorePlugin} class transformers
[11:47:05] [main/TRACE] [FML/]: Registering transformer codechicken.nei.asm.NEITransformer
[11:47:05] [main/DEBUG] [FML/]: Injection complete
[11:47:05] [main/DEBUG] [FML/]: Running coremod plugin for NEICorePlugin {codechicken.nei.asm.NEICorePlugin}
[11:47:05] [main/DEBUG] [FML/]: Running coremod plugin NEICorePlugin
[11:47:05] [main/DEBUG] [FML/]: Coremod plugin class NEICorePlugin run successfully
[11:47:05] [main/INFO] [LaunchWrapper/]: Calling tweak class cpw.mods.fml.relauncher.CoreModManager$FMLPluginWrapper
[11:47:05] [main/DEBUG] [FML/]: Injecting coremod CodeChickenCorePlugin {codechicken.core.launch.CodeChickenCorePlugin} class transformers
[11:47:05] [main/TRACE] [FML/]: Registering transformer codechicken.lib.asm.ClassHeirachyManager
[11:47:05] [main/TRACE] [FML/]: Registering transformer codechicken.core.asm.InterfaceDependancyTransformer
[11:47:05] [main/TRACE] [FML/]: Registering transformer codechicken.core.asm.TweakTransformer
[11:47:05] [main/TRACE] [FML/]: Registering transformer codechicken.core.asm.DelegatedTransformer
[11:47:05] [main/TRACE] [FML/]: Registering transformer codechicken.core.asm.DefaultImplementationTransformer
[11:47:05] [main/DEBUG] [FML/]: Injection complete
[11:47:05] [main/DEBUG] [FML/]: Running coremod plugin for CodeChickenCorePlugin {codechicken.core.launch.CodeChickenCorePlugin}
[11:47:05] [main/DEBUG] [FML/]: Running coremod plugin CodeChickenCorePlugin
[11:47:05] [main/DEBUG] [FML/]: Coremod plugin class CodeChickenCorePlugin run successfully
[11:47:05] [main/INFO] [LaunchWrapper/]: Calling tweak class cpw.mods.fml.relauncher.CoreModManager$FMLPluginWrapper
[11:47:05] [main/DEBUG] [FML/]: Injecting coremod DepLoader {codechicken.core.launch.DepLoader} class transformers
[11:47:05] [main/DEBUG] [FML/]: Injection complete
[11:47:05] [main/DEBUG] [FML/]: Running coremod plugin for DepLoader {codechicken.core.launch.DepLoader}
[11:47:05] [main/DEBUG] [FML/]: Running coremod plugin DepLoader
[11:47:05] [main/DEBUG] [FML/]: Coremod plugin class DepLoader run successfully
[11:47:05] [main/INFO] [LaunchWrapper/]: Calling tweak class cpw.mods.fml.relauncher.CoreModManager$FMLPluginWrapper
[11:47:05] [main/DEBUG] [FML/]: Injecting coremod CodeChickenCorePlugin {codechicken.core.launch.CodeChickenCorePlugin} class transformers
[11:47:05] [main/TRACE] [FML/]: Registering transformer codechicken.lib.asm.ClassHeirachyManager
[11:47:05] [main/TRACE] [FML/]: Registering transformer codechicken.core.asm.InterfaceDependancyTransformer
[11:47:05] [main/TRACE] [FML/]: Registering transformer codechicken.core.asm.TweakTransformer
[11:47:05] [main/TRACE] [FML/]: Registering transformer codechicken.core.asm.DelegatedTransformer
[11:47:05] [main/TRACE] [FML/]: Registering transformer codechicken.core.asm.DefaultImplementationTransformer
[11:47:05] [main/DEBUG] [FML/]: Injection complete
[11:47:05] [main/DEBUG] [FML/]: Running coremod plugin for CodeChickenCorePlugin {codechicken.core.launch.CodeChickenCorePlugin}
[11:47:05] [main/DEBUG] [FML/]: Running coremod plugin CodeChickenCorePlugin
[11:47:05] [main/DEBUG] [FML/]: Coremod plugin class CodeChickenCorePlugin run successfully
[11:47:05] [main/INFO] [LaunchWrapper/]: Calling tweak class cpw.mods.fml.relauncher.CoreModManager$FMLPluginWrapper
[11:47:05] [main/DEBUG] [FML/]: Injecting coremod DepLoader {codechicken.core.launch.DepLoader} class transformers
[11:47:05] [main/DEBUG] [FML/]: Injection complete
[11:47:05] [main/DEBUG] [FML/]: Running coremod plugin for DepLoader {codechicken.core.launch.DepLoader}
[11:47:05] [main/DEBUG] [FML/]: Running coremod plugin DepLoader
[11:47:05] [main/DEBUG] [FML/]: Coremod plugin class DepLoader run successfully
[11:47:05] [main/INFO] [LaunchWrapper/]: Calling tweak class cpw.mods.fml.relauncher.CoreModManager$FMLPluginWrapper
[11:47:05] [main/DEBUG] [FML/]: Injecting coremod NEICorePlugin {codechicken.nei.asm.NEICorePlugin} class transformers
[11:47:05] [main/TRACE] [FML/]: Registering transformer codechicken.nei.asm.NEITransformer
[11:47:05] [main/DEBUG] [FML/]: Injection complete
[11:47:05] [main/DEBUG] [FML/]: Running coremod plugin for NEICorePlugin {codechicken.nei.asm.NEICorePlugin}
[11:47:05] [main/DEBUG] [FML/]: Running coremod plugin NEICorePlugin
[11:47:05] [main/DEBUG] [FML/]: Coremod plugin class NEICorePlugin run successfully
[11:47:05] [main/INFO] [LaunchWrapper/]: Calling tweak class cpw.mods.fml.common.launcher.FMLDeobfTweaker
[11:47:05] [main/DEBUG] [FML/]: Loaded 57 rules from AccessTransformer config file fml_at.cfg
[11:47:05] [main/DEBUG] [FML/]: Loaded 89 rules from AccessTransformer config file forge_at.cfg
[11:47:05] [main/DEBUG] [FML/]: Loaded 57 rules from AccessTransformer config file fml_at.cfg
[11:47:05] [main/DEBUG] [FML/]: Loaded 57 rules from AccessTransformer config file fml_at.cfg
[11:47:05] [main/DEBUG] [FML/]: Loaded 11 rules from AccessTransformer mod jar file C:\Users\Connor\.gradle\caches\modules-2\files-2.1\codechicken\NotEnoughItems\1.7.10-1.0.4.106\2f540c1402d458270f055d59244906fe199e046\NotEnoughItems-1.7.10-1.0.4.106-dev.jar!META-INF/nei_at.cfg

[11:47:05] [main/DEBUG] [FML/]: Loaded 11 rules from AccessTransformer mod jar file C:\Users\Connor\Desktop\Projects\mc mod 1\forge\mods\NotEnoughItems-1.7.10-1.0.3.74-dev.jar!META-INF/nei_at.cfg

[11:47:05] [main/DEBUG] [FML/]: Validating minecraft
[11:47:06] [main/DEBUG] [FML/]: Minecraft validated, launching...
[11:47:06] [main/INFO] [LaunchWrapper/]: Calling tweak class net.minecraftforge.gradle.tweakers.AccessTransformerTweaker
[11:47:06] [main/DEBUG] [GradleStart/]: Reading CSV file: C:\Users\Connor\.gradle\caches\minecraft\net\minecraftforge\forge\1.7.10-10.13.4.1448-1.7.10\unpacked\conf\fields.csv
[11:47:06] [main/DEBUG] [GradleStart/]: Reading CSV file: C:\Users\Connor\.gradle\caches\minecraft\net\minecraftforge\forge\1.7.10-10.13.4.1448-1.7.10\unpacked\conf\methods.csv
[11:47:06] [main/INFO] [GradleStart/]: Remapping AccessTransformer rules...
[11:47:06] [main/INFO] [LaunchWrapper/]: Loading tweak class name cpw.mods.fml.common.launcher.TerminalTweaker
[11:47:06] [main/INFO] [LaunchWrapper/]: Calling tweak class cpw.mods.fml.common.launcher.TerminalTweaker
[11:47:06] [main/INFO] [LaunchWrapper/]: Launching wrapped minecraft {net.minecraft.client.main.Main}
[11:47:06] [main/DEBUG] [CCL ASM/]: Inserted super call into [net/minecraft/client/renderer/InventoryEffectRenderer.updateScreen()V]
[11:47:06] [main/DEBUG] [CCL ASM/]: Writing method [net/minecraft/client/gui/inventory/GuiContainer.setWorldAndResolution(Lnet/minecraft/client/Minecraft;II)V]
[11:47:06] [main/DEBUG] [CCL ASM/]: Writing method [net/minecraft/client/gui/inventory/GuiContainer.handleKeyboardInput()V]
[11:47:06] [main/DEBUG] [CCL ASM/]: Writing method [net/minecraft/client/gui/inventory/GuiContainer.handleKeyboardInput()V]
[11:47:06] [main/DEBUG] [CCL ASM/]: Writing method [net/minecraft/client/gui/inventory/GuiContainer.handleKeyboardInput()V]
[11:47:06] [main/DEBUG] [CCL ASM/]: Writing method [net/minecraft/client/gui/inventory/GuiContainer.handleMouseInput()V]
[11:47:06] [main/DEBUG] [CCL ASM/]: Writing method [net/minecraft/client/gui/inventory/GuiContainer.public_func_73869_a(CI)V]
[11:47:06] [main/DEBUG] [CCL ASM/]: Writing method [net/minecraft/client/gui/inventory/GuiContainer.public_func_146984_a(Lnet/minecraft/inventory/Slot;III)V]
[11:47:06] [main/DEBUG] [CCL ASM/]: Injecting before method [net/minecraft/client/gui/inventory/GuiContainer.drawScreen(IIF)V]
[11:47:06] [main/DEBUG] [CCL ASM/]: Injecting after method [net/minecraft/client/gui/inventory/GuiContainer.drawScreen(IIF)V] @ 138 - 140
[11:47:06] [main/DEBUG] [CCL ASM/]: Injecting after method [net/minecraft/client/gui/inventory/GuiContainer.drawScreen(IIF)V] @ 220 - 225
[11:47:06] [main/DEBUG] [CCL ASM/]: Replacing method [net/minecraft/client/gui/inventory/GuiContainer.drawScreen(IIF)V] @ 444 - 470
[11:47:06] [main/DEBUG] [CCL ASM/]: Replacing method [net/minecraft/client/gui/inventory/GuiContainer.drawItemStack(Lnet/minecraft/item/ItemStack;IILjava/lang/String;)V] @ 9 - 10
[11:47:06] [main/DEBUG] [CCL ASM/]: Replacing method [net/minecraft/client/gui/inventory/GuiContainer.drawItemStack(Lnet/minecraft/item/ItemStack;IILjava/lang/String;)V] @ 14 - 15
[11:47:06] [main/DEBUG] [CCL ASM/]: Replacing method [net/minecraft/client/gui/inventory/GuiContainer.func_146977_a(Lnet/minecraft/inventory/Slot;)V] @ 298 - 323
[11:47:06] [main/DEBUG] [CCL ASM/]: Injecting before method [net/minecraft/client/gui/inventory/GuiContainer.mouseClicked(III)V]
[11:47:06] [main/DEBUG] [CCL ASM/]: Replacing method [net/minecraft/client/gui/inventory/GuiContainer.mouseClicked(III)V] @ 259 - 260
[11:47:06] [main/DEBUG] [CCL ASM/]: Replacing method [net/minecraft/client/gui/inventory/GuiContainer.mouseClicked(III)V] @ 331 - 332
[11:47:06] [main/DEBUG] [CCL ASM/]: Replacing method [net/minecraft/client/gui/inventory/GuiContainer.mouseClickMove(IIIJ)V] @ 98 - 99
[11:47:06] [main/DEBUG] [CCL ASM/]: Replacing method [net/minecraft/client/gui/inventory/GuiContainer.mouseClickMove(IIIJ)V] @ 107 - 108
[11:47:06] [main/DEBUG] [CCL ASM/]: Replacing method [net/minecraft/client/gui/inventory/GuiContainer.mouseClickMove(IIIJ)V] @ 118 - 119
[11:47:06] [main/DEBUG] [CCL ASM/]: Replacing method [net/minecraft/client/gui/inventory/GuiContainer.mouseMovedOrUp(III)V] @ 158 - 159
[11:47:06] [main/DEBUG] [CCL ASM/]: Replacing method [net/minecraft/client/gui/inventory/GuiContainer.mouseMovedOrUp(III)V] @ 168 - 169
[11:47:06] [main/DEBUG] [CCL ASM/]: Replacing method [net/minecraft/client/gui/inventory/GuiContainer.mouseMovedOrUp(III)V] @ 287 - 288
[11:47:06] [main/DEBUG] [CCL ASM/]: Replacing method [net/minecraft/client/gui/inventory/GuiContainer.mouseMovedOrUp(III)V] @ 295 - 296
[11:47:06] [main/DEBUG] [CCL ASM/]: Replacing method [net/minecraft/client/gui/inventory/GuiContainer.mouseMovedOrUp(III)V] @ 314 - 315
[11:47:06] [main/DEBUG] [CCL ASM/]: Replacing method [net/minecraft/client/gui/inventory/GuiContainer.mouseMovedOrUp(III)V] @ 424 - 425
[11:47:06] [main/DEBUG] [CCL ASM/]: Replacing method [net/minecraft/client/gui/inventory/GuiContainer.mouseMovedOrUp(III)V] @ 454 - 455
[11:47:06] [main/DEBUG] [CCL ASM/]: Replacing method [net/minecraft/client/gui/inventory/GuiContainer.mouseMovedOrUp(III)V] @ 468 - 469
[11:47:06] [main/DEBUG] [CCL ASM/]: Replacing method [net/minecraft/client/gui/inventory/GuiContainer.mouseMovedOrUp(III)V] @ 497 - 498
[11:47:06] [main/DEBUG] [CCL ASM/]: Replacing method [net/minecraft/client/gui/inventory/GuiContainer.mouseMovedOrUp(III)V] @ 557 - 559
[11:47:06] [main/DEBUG] [CCL ASM/]: Replacing method [net/minecraft/client/gui/inventory/GuiContainer.keyTyped(CI)V] @ 54 - 55
[11:47:06] [main/DEBUG] [CCL ASM/]: Replacing method [net/minecraft/client/gui/inventory/GuiContainer.keyTyped(CI)V] @ 84 - 85
[11:47:06] [main/DEBUG] [CCL ASM/]: Replacing method [net/minecraft/client/gui/inventory/GuiContainer.checkHotbarKeys(I)Z] @ 41 - 42
[11:47:06] [main/DEBUG] [CCL ASM/]: Writing method [net/minecraft/client/gui/inventory/GuiContainer.managerHandleMouseClick(Lnet/minecraft/inventory/Slot;III)V]
[11:47:06] [main/DEBUG] [CCL ASM/]: Injecting after method [net/minecraft/client/gui/inventory/GuiContainer.mouseClickMove(IIIJ)V] @ 14 - 15
[11:47:06] [main/DEBUG] [CCL ASM/]: Injecting before method [net/minecraft/client/gui/inventory/GuiContainer.mouseMovedOrUp(III)V]
[11:47:06] [main/DEBUG] [CCL ASM/]: NEI: Injecting mouseUp call
[11:47:06] [main/DEBUG] [CCL ASM/]: Replacing method [net/minecraft/client/gui/inventory/GuiContainer.handleMouseClick(Lnet/minecraft/inventory/Slot;III)V] @ 10 - 26
[11:47:06] [main/DEBUG] [CCL ASM/]: Injecting before method [net/minecraft/client/gui/inventory/GuiContainer.keyTyped(CI)V]
[11:47:06] [main/DEBUG] [CCL ASM/]: Injecting after method [net/minecraft/client/gui/inventory/GuiContainer.updateScreen()V] @ 0 - 4
[11:47:06] [main/DEBUG] [CCL ASM/]: Writing method [net/minecraft/client/gui/inventory/GuiContainer.setWorldAndResolution(Lnet/minecraft/client/Minecraft;II)V]
[11:47:06] [main/DEBUG] [CCL ASM/]: Writing method [net/minecraft/client/gui/inventory/GuiContainer.handleKeyboardInput()V]
[11:47:06] [main/DEBUG] [CCL ASM/]: Writing method [net/minecraft/client/gui/inventory/GuiContainer.handleKeyboardInput()V]
[11:47:06] [main/DEBUG] [CCL ASM/]: Writing method [net/minecraft/client/gui/inventory/GuiContainer.handleKeyboardInput()V]
[11:47:06] [main/DEBUG] [CCL ASM/]: Writing method [net/minecraft/client/gui/inventory/GuiContainer.handleMouseInput()V]
[11:47:06] [main/DEBUG] [CCL ASM/]: Writing method [net/minecraft/client/gui/inventory/GuiContainer.public_func_73869_a(CI)V]
[11:47:06] [main/DEBUG] [CCL ASM/]: Writing method [net/minecraft/client/gui/inventory/GuiContainer.public_func_146984_a(Lnet/minecraft/inventory/Slot;III)V]
[11:47:06] [main/DEBUG] [CCL ASM/]: Injecting before method [net/minecraft/client/gui/inventory/GuiContainer.drawScreen(IIF)V]
[11:47:06] [main/DEBUG] [CCL ASM/]: Injecting after method [net/minecraft/client/gui/inventory/GuiContainer.drawScreen(IIF)V] @ 143 - 145
[11:47:06] [main/DEBUG] [CCL ASM/]: Injecting after method [net/minecraft/client/gui/inventory/GuiContainer.drawScreen(IIF)V] @ 231 - 236
[11:47:06] [main/ERROR] [LaunchWrapper/]: Unable to launch
java.lang.reflect.InvocationTargetException
	at sun.reflect.NativeMethodAccessorImpl.invoke0(Native Method) ~[?:1.8.0_60]
	at sun.reflect.NativeMethodAccessorImpl.invoke(Unknown Source) ~[?:1.8.0_60]
	at sun.reflect.DelegatingMethodAccessorImpl.invoke(Unknown Source) ~[?:1.8.0_60]
	at java.lang.reflect.Method.invoke(Unknown Source) ~[?:1.8.0_60]
	at net.minecraft.launchwrapper.Launch.launch(Launch.java:135) [launchwrapper-1.11.jar:?]
	at net.minecraft.launchwrapper.Launch.main(Launch.java:28) [launchwrapper-1.11.jar:?]
	at net.minecraftforge.gradle.GradleStartCommon.launch(Unknown Source) [start/:?]
	at GradleStart.main(Unknown Source) [start/:?]
Caused by: java.lang.NoClassDefFoundError: net/minecraft/client/gui/inventory/GuiInventory
	at net.minecraft.client.main.Main.main(Main.java:79) ~[Main.class:?]
	... 8 more
Caused by: java.lang.ClassNotFoundException: net.minecraft.client.gui.inventory.GuiInventory
	at net.minecraft.launchwrapper.LaunchClassLoader.findClass(LaunchClassLoader.java:191) ~[launchwrapper-1.11.jar:?]
	at java.lang.ClassLoader.loadClass(Unknown Source) ~[?:1.8.0_60]
	at java.lang.ClassLoader.loadClass(Unknown Source) ~[?:1.8.0_60]
	at net.minecraft.client.main.Main.main(Main.java:79) ~[Main.class:?]
	... 8 more
Caused by: java.lang.NoClassDefFoundError: net/minecraft/client/renderer/InventoryEffectRenderer
	at java.lang.ClassLoader.defineClass1(Native Method) ~[?:1.8.0_60]
	at java.lang.ClassLoader.defineClass(Unknown Source) ~[?:1.8.0_60]
	at java.security.SecureClassLoader.defineClass(Unknown Source) ~[?:1.8.0_60]
	at net.minecraft.launchwrapper.LaunchClassLoader.findClass(LaunchClassLoader.java:182) ~[launchwrapper-1.11.jar:?]
	at java.lang.ClassLoader.loadClass(Unknown Source) ~[?:1.8.0_60]
	at java.lang.ClassLoader.loadClass(Unknown Source) ~[?:1.8.0_60]
	at net.minecraft.client.main.Main.main(Main.java:79) ~[Main.class:?]
	... 8 more
Caused by: java.lang.ClassNotFoundException: net.minecraft.client.renderer.InventoryEffectRenderer
	at net.minecraft.launchwrapper.LaunchClassLoader.findClass(LaunchClassLoader.java:191) ~[launchwrapper-1.11.jar:?]
	at java.lang.ClassLoader.loadClass(Unknown Source) ~[?:1.8.0_60]
	at java.lang.ClassLoader.loadClass(Unknown Source) ~[?:1.8.0_60]
	at java.lang.ClassLoader.defineClass1(Native Method) ~[?:1.8.0_60]
	at java.lang.ClassLoader.defineClass(Unknown Source) ~[?:1.8.0_60]
	at java.security.SecureClassLoader.defineClass(Unknown Source) ~[?:1.8.0_60]
	at net.minecraft.launchwrapper.LaunchClassLoader.findClass(LaunchClassLoader.java:182) ~[launchwrapper-1.11.jar:?]
	at java.lang.ClassLoader.loadClass(Unknown Source) ~[?:1.8.0_60]
	at java.lang.ClassLoader.loadClass(Unknown Source) ~[?:1.8.0_60]
	at net.minecraft.client.main.Main.main(Main.java:79) ~[Main.class:?]
	... 8 more
Caused by: java.lang.NoClassDefFoundError: net/minecraft/client/gui/inventory/GuiContainer
	at java.lang.ClassLoader.defineClass1(Native Method) ~[?:1.8.0_60]
	at java.lang.ClassLoader.defineClass(Unknown Source) ~[?:1.8.0_60]
	at java.security.SecureClassLoader.defineClass(Unknown Source) ~[?:1.8.0_60]
	at net.minecraft.launchwrapper.LaunchClassLoader.findClass(LaunchClassLoader.java:182) ~[launchwrapper-1.11.jar:?]
	at java.lang.ClassLoader.loadClass(Unknown Source) ~[?:1.8.0_60]
	at java.lang.ClassLoader.loadClass(Unknown Source) ~[?:1.8.0_60]
	at java.lang.ClassLoader.defineClass1(Native Method) ~[?:1.8.0_60]
	at java.lang.ClassLoader.defineClass(Unknown Source) ~[?:1.8.0_60]
	at java.security.SecureClassLoader.defineClass(Unknown Source) ~[?:1.8.0_60]
	at net.minecraft.launchwrapper.LaunchClassLoader.findClass(LaunchClassLoader.java:182) ~[launchwrapper-1.11.jar:?]
	at java.lang.ClassLoader.loadClass(Unknown Source) ~[?:1.8.0_60]
	at java.lang.ClassLoader.loadClass(Unknown Source) ~[?:1.8.0_60]
	at net.minecraft.client.main.Main.main(Main.java:79) ~[Main.class:?]
	... 8 more
Caused by: java.lang.ClassNotFoundException: net.minecraft.client.gui.inventory.GuiContainer
	at net.minecraft.launchwrapper.LaunchClassLoader.findClass(LaunchClassLoader.java:191) ~[launchwrapper-1.11.jar:?]
	at java.lang.ClassLoader.loadClass(Unknown Source) ~[?:1.8.0_60]
	at java.lang.ClassLoader.loadClass(Unknown Source) ~[?:1.8.0_60]
	at java.lang.ClassLoader.defineClass1(Native Method) ~[?:1.8.0_60]
	at java.lang.ClassLoader.defineClass(Unknown Source) ~[?:1.8.0_60]
	at java.security.SecureClassLoader.defineClass(Unknown Source) ~[?:1.8.0_60]
	at net.minecraft.launchwrapper.LaunchClassLoader.findClass(LaunchClassLoader.java:182) ~[launchwrapper-1.11.jar:?]
	at java.lang.ClassLoader.loadClass(Unknown Source) ~[?:1.8.0_60]
	at java.lang.ClassLoader.loadClass(Unknown Source) ~[?:1.8.0_60]
	at java.lang.ClassLoader.defineClass1(Native Method) ~[?:1.8.0_60]
	at java.lang.ClassLoader.defineClass(Unknown Source) ~[?:1.8.0_60]
	at java.security.SecureClassLoader.defineClass(Unknown Source) ~[?:1.8.0_60]
	at net.minecraft.launchwrapper.LaunchClassLoader.findClass(LaunchClassLoader.java:182) ~[launchwrapper-1.11.jar:?]
	at java.lang.ClassLoader.loadClass(Unknown Source) ~[?:1.8.0_60]
	at java.lang.ClassLoader.loadClass(Unknown Source) ~[?:1.8.0_60]
	at net.minecraft.client.main.Main.main(Main.java:79) ~[Main.class:?]
	... 8 more
Caused by: java.lang.RuntimeException: java.lang.RuntimeException: Error transforming method: [net/minecraft/client/gui/inventory/GuiContainer.drawScreen(IIF)V]
	at codechicken.nei.asm.NEITransformer.transform(NEITransformer.java:242) ~[NotEnoughItems-1.7.10-1.0.4.106-dev.jar:?]
	at net.minecraft.launchwrapper.LaunchClassLoader.runTransformers(LaunchClassLoader.java:279) ~[launchwrapper-1.11.jar:?]
	at net.minecraft.launchwrapper.LaunchClassLoader.findClass(LaunchClassLoader.java:176) ~[launchwrapper-1.11.jar:?]
	at java.lang.ClassLoader.loadClass(Unknown Source) ~[?:1.8.0_60]
	at java.lang.ClassLoader.loadClass(Unknown Source) ~[?:1.8.0_60]
	at java.lang.ClassLoader.defineClass1(Native Method) ~[?:1.8.0_60]
	at java.lang.ClassLoader.defineClass(Unknown Source) ~[?:1.8.0_60]
	at java.security.SecureClassLoader.defineClass(Unknown Source) ~[?:1.8.0_60]
	at net.minecraft.launchwrapper.LaunchClassLoader.findClass(LaunchClassLoader.java:182) ~[launchwrapper-1.11.jar:?]
	at java.lang.ClassLoader.loadClass(Unknown Source) ~[?:1.8.0_60]
	at java.lang.ClassLoader.loadClass(Unknown Source) ~[?:1.8.0_60]
	at java.lang.ClassLoader.defineClass1(Native Method) ~[?:1.8.0_60]
	at java.lang.ClassLoader.defineClass(Unknown Source) ~[?:1.8.0_60]
	at java.security.SecureClassLoader.defineClass(Unknown Source) ~[?:1.8.0_60]
	at net.minecraft.launchwrapper.LaunchClassLoader.findClass(LaunchClassLoader.java:182) ~[launchwrapper-1.11.jar:?]
	at java.lang.ClassLoader.loadClass(Unknown Source) ~[?:1.8.0_60]
	at java.lang.ClassLoader.loadClass(Unknown Source) ~[?:1.8.0_60]
	at net.minecraft.client.main.Main.main(Main.java:79) ~[Main.class:?]
	... 8 more
Caused by: java.lang.RuntimeException: Error transforming method: [net/minecraft/client/gui/inventory/GuiContainer.drawScreen(IIF)V]
	at codechicken.lib.asm.ModularASMTransformer$MethodTransformer.transform(ModularASMTransformer.java:90) ~[CodeChickenLib-1.7.10-1.1.3.136-dev.jar:?]
	at codechicken.lib.asm.ModularASMTransformer$ClassNodeTransformerList.transform(ModularASMTransformer.java:36) ~[CodeChickenLib-1.7.10-1.1.3.136-dev.jar:?]
	at codechicken.lib.asm.ModularASMTransformer.transform(ModularASMTransformer.java:283) ~[CodeChickenLib-1.7.10-1.1.3.136-dev.jar:?]
	at codechicken.nei.asm.NEITransformer.transform(NEITransformer.java:240) ~[NotEnoughItems-1.7.10-1.0.4.106-dev.jar:?]
	at net.minecraft.launchwrapper.LaunchClassLoader.runTransformers(LaunchClassLoader.java:279) ~[launchwrapper-1.11.jar:?]
	at net.minecraft.launchwrapper.LaunchClassLoader.findClass(LaunchClassLoader.java:176) ~[launchwrapper-1.11.jar:?]
	at java.lang.ClassLoader.loadClass(Unknown Source) ~[?:1.8.0_60]
	at java.lang.ClassLoader.loadClass(Unknown Source) ~[?:1.8.0_60]
	at java.lang.ClassLoader.defineClass1(Native Method) ~[?:1.8.0_60]
	at java.lang.ClassLoader.defineClass(Unknown Source) ~[?:1.8.0_60]
	at java.security.SecureClassLoader.defineClass(Unknown Source) ~[?:1.8.0_60]
	at net.minecraft.launchwrapper.LaunchClassLoader.findClass(LaunchClassLoader.java:182) ~[launchwrapper-1.11.jar:?]
	at java.lang.ClassLoader.loadClass(Unknown Source) ~[?:1.8.0_60]
	at java.lang.ClassLoader.loadClass(Unknown Source) ~[?:1.8.0_60]
	at java.lang.ClassLoader.defineClass1(Native Method) ~[?:1.8.0_60]
	at java.lang.ClassLoader.defineClass(Unknown Source) ~[?:1.8.0_60]
	at java.security.SecureClassLoader.defineClass(Unknown Source) ~[?:1.8.0_60]
	at net.minecraft.launchwrapper.LaunchClassLoader.findClass(LaunchClassLoader.java:182) ~[launchwrapper-1.11.jar:?]
	at java.lang.ClassLoader.loadClass(Unknown Source) ~[?:1.8.0_60]
	at java.lang.ClassLoader.loadClass(Unknown Source) ~[?:1.8.0_60]
	at net.minecraft.client.main.Main.main(Main.java:79) ~[Main.class:?]
	... 8 more
Caused by: java.lang.RuntimeException: Needle not found in Haystack:
    ALOAD 0
    GETFIELD net/minecraft/client/gui/inventory/GuiContainer.manager : Lcodechicken/nei/guihook/GuiContainerManager;
    INVOKEVIRTUAL codechicken/nei/guihook/GuiContainerManager.preDraw ()V
   L0
    LINENUMBER 189 L0
    ALOAD 0
    GETFIELD net/minecraft/client/gui/inventory/GuiContainer.manager : Lcodechicken/nei/guihook/GuiContainerManager;
    INVOKEVIRTUAL codechicken/nei/guihook/GuiContainerManager.preDraw ()V
   L1
    LINENUMBER 90 L1
    ALOAD 0
    INVOKEVIRTUAL net/minecraft/client/gui/inventory/GuiContainer.drawDefaultBackground ()V
   L2
    LINENUMBER 91 L2
    ALOAD 0
    GETFIELD net/minecraft/client/gui/inventory/GuiContainer.guiLeft : I
    ISTORE 4
   L3
    LINENUMBER 92 L3
    ALOAD 0
    GETFIELD net/minecraft/client/gui/inventory/GuiContainer.guiTop : I
    ISTORE 5
   L4
    LINENUMBER 93 L4
    ALOAD 0
    FLOAD 3
    ILOAD 1
    ILOAD 2
    INVOKEVIRTUAL net/minecraft/client/gui/inventory/GuiContainer.drawGuiContainerBackgroundLayer (FII)V
   L5
    LINENUMBER 94 L5
    LDC 32826
    INVOKESTATIC org/lwjgl/opengl/GL11.glDisable (I)V
   L6
    LINENUMBER 95 L6
    INVOKESTATIC net/minecraft/client/renderer/RenderHelper.disableStandardItemLighting ()V
   L7
    LINENUMBER 96 L7
    SIPUSH 2896
    INVOKESTATIC org/lwjgl/opengl/GL11.glDisable (I)V
   L8
    LINENUMBER 97 L8
    SIPUSH 2929
    INVOKESTATIC org/lwjgl/opengl/GL11.glDisable (I)V
   L9
    LINENUMBER 98 L9
    ALOAD 0
    ILOAD 1
    ILOAD 2
    FLOAD 3
    INVOKESPECIAL net/minecraft/client/gui/GuiScreen.drawScreen (IIF)V
   L10
    LINENUMBER 99 L10
    INVOKESTATIC net/minecraft/client/renderer/RenderHelper.enableGUIStandardItemLighting ()V
   L11
    LINENUMBER 100 L11
    INVOKESTATIC org/lwjgl/opengl/GL11.glPushMatrix ()V
   L12
    LINENUMBER 101 L12
    ILOAD 4
    I2F
    ILOAD 5
    I2F
    FCONST_0
    INVOKESTATIC org/lwjgl/opengl/GL11.glTranslatef (FFF)V
   L13
    LINENUMBER 102 L13
    FCONST_1
    FCONST_1
    FCONST_1
    FCONST_1
    INVOKESTATIC org/lwjgl/opengl/GL11.glColor4f (FFFF)V
   L14
    LINENUMBER 103 L14
    LDC 32826
    INVOKESTATIC org/lwjgl/opengl/GL11.glEnable (I)V
   L15
    LINENUMBER 104 L15
    ALOAD 0
    ACONST_NULL
    PUTFIELD net/minecraft/client/gui/inventory/GuiContainer.theSlot : Lnet/minecraft/inventory/Slot;
   L16
    LINENUMBER 105 L16
    SIPUSH 240
    ISTORE 6
   L17
    LINENUMBER 106 L17
    SIPUSH 240
    ISTORE 7
   L18
    LINENUMBER 107 L18
    GETSTATIC net/minecraft/client/renderer/OpenGlHelper.lightmapTexUnit : I
    ILOAD 6
    I2F
    FCONST_1
    FDIV
    ILOAD 7
    I2F
    FCONST_1
    FDIV
    INVOKESTATIC net/minecraft/client/renderer/OpenGlHelper.setLightmapTextureCoords (IFF)V
   L19
    LINENUMBER 108 L19
    FCONST_1
    FCONST_1
    FCONST_1
    FCONST_1
    INVOKESTATIC org/lwjgl/opengl/GL11.glColor4f (FFFF)V
   L20
    LINENUMBER 111 L20
    ICONST_0
    ISTORE 8
   L21
   FRAME FULL [net/minecraft/client/gui/inventory/GuiContainer I I F I I I I I] []
    ILOAD 8
    ALOAD 0
    GETFIELD net/minecraft/client/gui/inventory/GuiContainer.inventorySlots : Lnet/minecraft/inventory/Container;
    GETFIELD net/minecraft/inventory/Container.inventorySlots : Ljava/util/List;
    INVOKEINTERFACE java/util/List.size ()I
    IF_ICMPGE L22
   L23
    LINENUMBER 113 L23
    ALOAD 0
    GETFIELD net/minecraft/client/gui/inventory/GuiContainer.inventorySlots : Lnet/minecraft/inventory/Container;
    GETFIELD net/minecraft/inventory/Container.inventorySlots : Ljava/util/List;
    ILOAD 8
    INVOKEINTERFACE java/util/List.get (I)Ljava/lang/Object;
    CHECKCAST net/minecraft/inventory/Slot
    ASTORE 9
   L24
    LINENUMBER 114 L24
    ALOAD 0
    ALOAD 9
    INVOKESPECIAL net/minecraft/client/gui/inventory/GuiContainer.func_146977_a (Lnet/minecraft/inventory/Slot;)V
   L25
    LINENUMBER 116 L25
    ALOAD 0
    ALOAD 9
    ILOAD 1
    ILOAD 2
    INVOKESPECIAL net/minecraft/client/gui/inventory/GuiContainer.isMouseOverSlot (Lnet/minecraft/inventory/Slot;II)Z
    IFEQ L26
    ALOAD 9
    INVOKEVIRTUAL net/minecraft/inventory/Slot.func_111238_b ()Z
    IFEQ L26
    ALOAD 0
    GETFIELD net/minecraft/client/gui/inventory/GuiContainer.manager : Lcodechicken/nei/guihook/GuiContainerManager;
    ILOAD 1
    ILOAD 2
    INVOKEVIRTUAL codechicken/nei/guihook/GuiContainerManager.objectUnderMouse (II)Z
    IFNE L26
    ALOAD 0
    GETFIELD net/minecraft/client/gui/inventory/GuiContainer.manager : Lcodechicken/nei/guihook/GuiContainerManager;
    ILOAD 1
    ILOAD 2
    INVOKEVIRTUAL codechicken/nei/guihook/GuiContainerManager.objectUnderMouse (II)Z
    IFNE L26
   L27
    LINENUMBER 118 L27
    ALOAD 0
    ALOAD 9
    PUTFIELD net/minecraft/client/gui/inventory/GuiContainer.theSlot : Lnet/minecraft/inventory/Slot;
   L28
    LINENUMBER 119 L28
    SIPUSH 2896
    INVOKESTATIC org/lwjgl/opengl/GL11.glDisable (I)V
   L29
    LINENUMBER 120 L29
    SIPUSH 2929
    INVOKESTATIC org/lwjgl/opengl/GL11.glDisable (I)V
   L30
    LINENUMBER 121 L30
    ALOAD 9
    GETFIELD net/minecraft/inventory/Slot.xDisplayPosition : I
    ISTORE 10
   L31
    LINENUMBER 122 L31
    ALOAD 9
    GETFIELD net/minecraft/inventory/Slot.yDisplayPosition : I
    ISTORE 11
   L32
    LINENUMBER 123 L32
    ICONST_1
    ICONST_1
    ICONST_1
    ICONST_0
    INVOKESTATIC org/lwjgl/opengl/GL11.glColorMask (ZZZZ)V
   L33
    LINENUMBER 124 L33
    ALOAD 0
    ILOAD 10
    ILOAD 11
    ILOAD 10
    BIPUSH 16
    IADD
    ILOAD 11
    BIPUSH 16
    IADD
    LDC -2130706433
    LDC -2130706433
    INVOKEVIRTUAL net/minecraft/client/gui/inventory/GuiContainer.drawGradientRect (IIIIII)V
   L34
    LINENUMBER 125 L34
    ICONST_1
    ICONST_1
    ICONST_1
    ICONST_1
    INVOKESTATIC org/lwjgl/opengl/GL11.glColorMask (ZZZZ)V
   L35
    LINENUMBER 126 L35
    SIPUSH 2896
    INVOKESTATIC org/lwjgl/opengl/GL11.glEnable (I)V
   L36
    LINENUMBER 127 L36
    SIPUSH 2929
    INVOKESTATIC org/lwjgl/opengl/GL11.glEnable (I)V
   L26
    LINENUMBER 111 L26
   FRAME FULL [net/minecraft/client/gui/inventory/GuiContainer I I F I I I I I net/minecraft/inventory/Slot] []
    IINC 8 1
    GOTO L21
   L22
    LINENUMBER 133 L22
   FRAME FULL [net/minecraft/client/gui/inventory/GuiContainer I I F I I I I I] []
    SIPUSH 2896
    INVOKESTATIC org/lwjgl/opengl/GL11.glDisable (I)V
   L37
    LINENUMBER 134 L37
    ALOAD 0
    ILOAD 1
    ILOAD 2
    INVOKEVIRTUAL net/minecraft/client/gui/inventory/GuiContainer.drawGuiContainerForegroundLayer (II)V
   L38
    LINENUMBER 135 L38
    SIPUSH 2896
    INVOKESTATIC org/lwjgl/opengl/GL11.glEnable (I)V
    ALOAD 0
    GETFIELD net/minecraft/client/gui/inventory/GuiContainer.manager : Lcodechicken/nei/guihook/GuiContainerManager;
    ILOAD 1
    ILOAD 2
    INVOKEVIRTUAL codechicken/nei/guihook/GuiContainerManager.renderObjects (II)V
    ALOAD 0
    GETFIELD net/minecraft/client/gui/inventory/GuiContainer.manager : Lcodechicken/nei/guihook/GuiContainerManager;
    ILOAD 1
    ILOAD 2
    INVOKEVIRTUAL codechicken/nei/guihook/GuiContainerManager.renderObjects (II)V
   L39
    LINENUMBER 136 L39
    ALOAD 0
    GETFIELD net/minecraft/client/gui/inventory/GuiContainer.mc : Lnet/minecraft/client/Minecraft;
    GETFIELD net/minecraft/client/Minecraft.thePlayer : Lnet/minecraft/client/entity/EntityClientPlayerMP;
    GETFIELD net/minecraft/client/entity/EntityClientPlayerMP.inventory : Lnet/minecraft/entity/player/InventoryPlayer;
    ASTORE 8
   L40
    LINENUMBER 137 L40
    ALOAD 0
    GETFIELD net/minecraft/client/gui/inventory/GuiContainer.draggedStack : Lnet/minecraft/item/ItemStack;
    IFNONNULL L41
    ALOAD 8
    INVOKEVIRTUAL net/minecraft/entity/player/InventoryPlayer.getItemStack ()Lnet/minecraft/item/ItemStack;
    GOTO L42
   L41
   FRAME FULL [net/minecraft/client/gui/inventory/GuiContainer I I F I I I I net/minecraft/entity/player/InventoryPlayer] []
    ALOAD 0
    GETFIELD net/minecraft/client/gui/inventory/GuiContainer.draggedStack : Lnet/minecraft/item/ItemStack;
   L42
   FRAME FULL [net/minecraft/client/gui/inventory/GuiContainer I I F I I I I net/minecraft/entity/player/InventoryPlayer] [net/minecraft/item/ItemStack]
    ASTORE 9
   L43
    LINENUMBER 139 L43
    ALOAD 9
    IFNULL L44
   L45
    LINENUMBER 141 L45
    BIPUSH 8
    ISTORE 10
   L46
    LINENUMBER 142 L46
    ALOAD 0
    GETFIELD net/minecraft/client/gui/inventory/GuiContainer.draggedStack : Lnet/minecraft/item/ItemStack;
    IFNONNULL L47
    BIPUSH 8
    GOTO L48
   L47
   FRAME FULL [net/minecraft/client/gui/inventory/GuiContainer I I F I I I I net/minecraft/entity/player/InventoryPlayer net/minecraft/item/ItemStack I] []
    BIPUSH 16
   L48
   FRAME FULL [net/minecraft/client/gui/inventory/GuiContainer I I F I I I I net/minecraft/entity/player/InventoryPlayer net/minecraft/item/ItemStack I] [I]
    ISTORE 11
   L49
    LINENUMBER 143 L49
    ACONST_NULL
    ASTORE 12
   L50
    LINENUMBER 145 L50
    ALOAD 0
    GETFIELD net/minecraft/client/gui/inventory/GuiContainer.draggedStack : Lnet/minecraft/item/ItemStack;
    IFNULL L51
    ALOAD 0
    GETFIELD net/minecraft/client/gui/inventory/GuiContainer.isRightMouseClick : Z
    IFEQ L51
   L52
    LINENUMBER 147 L52
    ALOAD 9
    INVOKEVIRTUAL net/minecraft/item/ItemStack.copy ()Lnet/minecraft/item/ItemStack;
    ASTORE 9
   L53
    LINENUMBER 148 L53
    ALOAD 9
    ALOAD 9
    GETFIELD net/minecraft/item/ItemStack.stackSize : I
    I2F
    FCONST_2
    FDIV
    INVOKESTATIC net/minecraft/util/MathHelper.ceiling_float_int (F)I
    PUTFIELD net/minecraft/item/ItemStack.stackSize : I
    GOTO L54
   L51
    LINENUMBER 150 L51
   FRAME FULL [net/minecraft/client/gui/inventory/GuiContainer I I F I I I I net/minecraft/entity/player/InventoryPlayer net/minecraft/item/ItemStack I I N] []
    ALOAD 0
    GETFIELD net/minecraft/client/gui/inventory/GuiContainer.field_147007_t : Z
    IFEQ L54
    ALOAD 0
    GETFIELD net/minecraft/client/gui/inventory/GuiContainer.field_147008_s : Ljava/util/Set;
    INVOKEINTERFACE java/util/Set.size ()I
    ICONST_1
    IF_ICMPLE L54
   L55
    LINENUMBER 152 L55
    ALOAD 9
    INVOKEVIRTUAL net/minecraft/item/ItemStack.copy ()Lnet/minecraft/item/ItemStack;
    ASTORE 9
   L56
    LINENUMBER 153 L56
    ALOAD 9
    ALOAD 0
    GETFIELD net/minecraft/client/gui/inventory/GuiContainer.field_146996_I : I
    PUTFIELD net/minecraft/item/ItemStack.stackSize : I
   L57
    LINENUMBER 155 L57
    ALOAD 9
    GETFIELD net/minecraft/item/ItemStack.stackSize : I
    IFNE L54
   L58
    LINENUMBER 157 L58
    NEW java/lang/StringBuilder
    DUP
    INVOKESPECIAL java/lang/StringBuilder.<init> ()V
    LDC ""
    INVOKEVIRTUAL java/lang/StringBuilder.append (Ljava/lang/String;)Ljava/lang/StringBuilder;
    GETSTATIC net/minecraft/util/EnumChatFormatting.YELLOW : Lnet/minecraft/util/EnumChatFormatting;
    INVOKEVIRTUAL java/lang/StringBuilder.append (Ljava/lang/Object;)Ljava/lang/StringBuilder;
    LDC "0"
    INVOKEVIRTUAL java/lang/StringBuilder.append (Ljava/lang/String;)Ljava/lang/StringBuilder;
    INVOKEVIRTUAL java/lang/StringBuilder.toString ()Ljava/lang/String;
    ASTORE 12
   L54
    LINENUMBER 161 L54
   FRAME FULL [net/minecraft/client/gui/inventory/GuiContainer I I F I I I I net/minecraft/entity/player/InventoryPlayer net/minecraft/item/ItemStack I I java/lang/String] []
    ALOAD 0
    ALOAD 9
    ILOAD 1
    ILOAD 4
    ISUB
    ILOAD 10
    ISUB
    ILOAD 2
    ILOAD 5
    ISUB
    ILOAD 11
    ISUB
    ALOAD 12
    INVOKESPECIAL net/minecraft/client/gui/inventory/GuiContainer.drawItemStack (Lnet/minecraft/item/ItemStack;IILjava/lang/String;)V
   L44
    LINENUMBER 164 L44
   FRAME FULL [net/minecraft/client/gui/inventory/GuiContainer I I F I I I I net/minecraft/entity/player/InventoryPlayer net/minecraft/item/ItemStack] []
    ALOAD 0
    GETFIELD net/minecraft/client/gui/inventory/GuiContainer.returningStack : Lnet/minecraft/item/ItemStack;
    IFNULL L59
   L60
    LINENUMBER 166 L60
    INVOKESTATIC net/minecraft/client/Minecraft.getSystemTime ()J
    ALOAD 0
    GETFIELD net/minecraft/client/gui/inventory/GuiContainer.returningStackTime : J
    LSUB
    L2F
    LDC 100.0
    FDIV
    FSTORE 10
   L61
    LINENUMBER 168 L61
    FLOAD 10
    FCONST_1
    FCMPL
    IFLT L62
   L63
    LINENUMBER 170 L63
    FCONST_1
    FSTORE 10
   L64
    LINENUMBER 171 L64
    ALOAD 0
    ACONST_NULL
    PUTFIELD net/minecraft/client/gui/inventory/GuiContainer.returningStack : Lnet/minecraft/item/ItemStack;
   L62
    LINENUMBER 174 L62
   FRAME FULL [net/minecraft/client/gui/inventory/GuiContainer I I F I I I I net/minecraft/entity/player/InventoryPlayer net/minecraft/item/ItemStack F] []
    ALOAD 0
    GETFIELD net/minecraft/client/gui/inventory/GuiContainer.returningStackDestSlot : Lnet/minecraft/inventory/Slot;
    GETFIELD net/minecraft/inventory/Slot.xDisplayPosition : I
    ALOAD 0
    GETFIELD net/minecraft/client/gui/inventory/GuiContainer.field_147011_y : I
    ISUB
    ISTORE 11
   L65
    LINENUMBER 175 L65
    ALOAD 0
    GETFIELD net/minecraft/client/gui/inventory/GuiContainer.returningStackDestSlot : Lnet/minecraft/inventory/Slot;
    GETFIELD net/minecraft/inventory/Slot.yDisplayPosition : I
    ALOAD 0
    GETFIELD net/minecraft/client/gui/inventory/GuiContainer.field_147010_z : I
    ISUB
    ISTORE 12
   L66
    LINENUMBER 176 L66
    ALOAD 0
    GETFIELD net/minecraft/client/gui/inventory/GuiContainer.field_147011_y : I
    ILOAD 11
    I2F
    FLOAD 10
    FMUL
    F2I
    IADD
    ISTORE 13
   L67
    LINENUMBER 177 L67
    ALOAD 0
    GETFIELD net/minecraft/client/gui/inventory/GuiContainer.field_147010_z : I
    ILOAD 12
    I2F
    FLOAD 10
    FMUL
    F2I
    IADD
    ISTORE 14
   L68
    LINENUMBER 178 L68
    ALOAD 0
    ALOAD 0
    GETFIELD net/minecraft/client/gui/inventory/GuiContainer.returningStack : Lnet/minecraft/item/ItemStack;
    ILOAD 13
    ILOAD 14
    ACONST_NULL
    CHECKCAST java/lang/String
    INVOKESPECIAL net/minecraft/client/gui/inventory/GuiContainer.drawItemStack (Lnet/minecraft/item/ItemStack;IILjava/lang/String;)V
   L59
    LINENUMBER 181 L59
   FRAME FULL [net/minecraft/client/gui/inventory/GuiContainer I I F I I I I net/minecraft/entity/player/InventoryPlayer net/minecraft/item/ItemStack] []
    INVOKESTATIC org/lwjgl/opengl/GL11.glPopMatrix ()V
    ALOAD 0
    GETFIELD net/minecraft/client/gui/inventory/GuiContainer.manager : Lcodechicken/nei/guihook/GuiContainerManager;
    ILOAD 1
    ILOAD 2
    INVOKEVIRTUAL codechicken/nei/guihook/GuiContainerManager.renderToolTips (II)V
    SIPUSH 2896
    INVOKESTATIC org/lwjgl/opengl/GL11.glEnable (I)V
   L69
    LINENUMBER 190 L69
    SIPUSH 2929
    INVOKESTATIC org/lwjgl/opengl/GL11.glEnable (I)V
   L70
    LINENUMBER 191 L70
    INVOKESTATIC net/minecraft/client/renderer/RenderHelper.enableStandardItemLighting ()V
   L71
    LINENUMBER 192 L71
    RETURN
   L72


    ALOAD 8
    INVOKEVIRTUAL net/minecraft/entity/player/InventoryPlayer.getItemStack ()Lnet/minecraft/item/ItemStack;
    IFNONNULL L0
    ALOAD 0
    GETFIELD net/minecraft/client/gui/inventory/GuiContainer.theSlot : Lnet/minecraft/inventory/Slot;
    IFNULL L0
    ALOAD 0
    GETFIELD net/minecraft/client/gui/inventory/GuiContainer.theSlot : Lnet/minecraft/inventory/Slot;
    INVOKEVIRTUAL net/minecraft/inventory/Slot.getHasStack ()Z
    IFEQ L0
    ALOAD 0
    GETFIELD net/minecraft/client/gui/inventory/GuiContainer.theSlot : Lnet/minecraft/inventory/Slot;
    INVOKEVIRTUAL net/minecraft/inventory/Slot.getStack ()Lnet/minecraft/item/ItemStack;
    ASTORE 10
    ALOAD 0
    ALOAD 10
    ILOAD 1
    ILOAD 2
    INVOKEVIRTUAL net/minecraft/client/gui/inventory/GuiContainer.renderToolTip (Lnet/minecraft/item/ItemStack;II)V
   L0

	at codechicken.lib.asm.InsnComparator.findN(InsnComparator.java:181) ~[CodeChickenLib-1.7.10-1.1.3.136-dev.jar:?]
	at codechicken.lib.asm.InsnComparator.findN(InsnComparator.java:187) ~[CodeChickenLib-1.7.10-1.1.3.136-dev.jar:?]
	at codechicken.lib.asm.ModularASMTransformer$MethodReplacer.transform(ModularASMTransformer.java:234) ~[CodeChickenLib-1.7.10-1.1.3.136-dev.jar:?]
	at codechicken.lib.asm.ModularASMTransformer$MethodTransformer.transform(ModularASMTransformer.java:88) ~[CodeChickenLib-1.7.10-1.1.3.136-dev.jar:?]
	at codechicken.lib.asm.ModularASMTransformer$ClassNodeTransformerList.transform(ModularASMTransformer.java:36) ~[CodeChickenLib-1.7.10-1.1.3.136-dev.jar:?]
	at codechicken.lib.asm.ModularASMTransformer.transform(ModularASMTransformer.java:283) ~[CodeChickenLib-1.7.10-1.1.3.136-dev.jar:?]
	at codechicken.nei.asm.NEITransformer.transform(NEITransformer.java:240) ~[NotEnoughItems-1.7.10-1.0.4.106-dev.jar:?]
	at net.minecraft.launchwrapper.LaunchClassLoader.runTransformers(LaunchClassLoader.java:279) ~[launchwrapper-1.11.jar:?]
	at net.minecraft.launchwrapper.LaunchClassLoader.findClass(LaunchClassLoader.java:176) ~[launchwrapper-1.11.jar:?]
	at java.lang.ClassLoader.loadClass(Unknown Source) ~[?:1.8.0_60]
	at java.lang.ClassLoader.loadClass(Unknown Source) ~[?:1.8.0_60]
	at java.lang.ClassLoader.defineClass1(Native Method) ~[?:1.8.0_60]
	at java.lang.ClassLoader.defineClass(Unknown Source) ~[?:1.8.0_60]
	at java.security.SecureClassLoader.defineClass(Unknown Source) ~[?:1.8.0_60]
	at net.minecraft.launchwrapper.LaunchClassLoader.findClass(LaunchClassLoader.java:182) ~[launchwrapper-1.11.jar:?]
	at java.lang.ClassLoader.loadClass(Unknown Source) ~[?:1.8.0_60]
	at java.lang.ClassLoader.loadClass(Unknown Source) ~[?:1.8.0_60]
	at java.lang.ClassLoader.defineClass1(Native Method) ~[?:1.8.0_60]
	at java.lang.ClassLoader.defineClass(Unknown Source) ~[?:1.8.0_60]
	at java.security.SecureClassLoader.defineClass(Unknown Source) ~[?:1.8.0_60]
	at net.minecraft.launchwrapper.LaunchClassLoader.findClass(LaunchClassLoader.java:182) ~[launchwrapper-1.11.jar:?]
	at java.lang.ClassLoader.loadClass(Unknown Source) ~[?:1.8.0_60]
	at java.lang.ClassLoader.loadClass(Unknown Source) ~[?:1.8.0_60]
	at net.minecraft.client.main.Main.main(Main.java:79) ~[Main.class:?]
	... 8 more
